rss2bsky/__init__.py
rss2bsky/__main__.py
rss2bsky/main.py
rss2bsky-0.1.4.dist-info/METADATA
rss2bsky-0.1.4.dist-info/WHEEL
rss2bsky-0.1.4.dist-info/entry_points.txt
rss2bsky-0.1.4.dist-info/licenses/LICENSE
rss2bsky-0.1.4.dist-info/RECORD
