Metadata-Version: 2.3
Name: rss2bsky
Version: 0.1.4
Summary: Crosspost RSS Feed to Bluesky
Project-URL: Homepage, https://github.com/rochacbruno/rss2bsky
Project-URL: Repository, https://github.com/rochacbruno/rss2bsky
Author-email: Bruno Rocha <rochacbruno@gmail.com>
Maintainer-email: Bruno Rocha <rochacbruno@gmail.com>
License:                     GNU AFFERO GENERAL PUBLIC LICENSE
License-File: LICENSE
Keywords: Bluesky,atproto,cross posting,fediverse,mastodon,rss
Requires-Python: >=3.10
Requires-Dist: atproto>=0.0.54
Requires-Dist: dynaconf>=3.2.6
Requires-Dist: feedparser>=6.0.11
Requires-Dist: httpx>=0.26.0
Requires-Dist: taskipy>=1.13.0
